myproj/__init__.py
myproj/__main__.py
langchain_extra-0.0.0rc0.dist-info/METADATA
langchain_extra-0.0.0rc0.dist-info/WHEEL
langchain_extra-0.0.0rc0.dist-info/top_level.txt
langchain_extra-0.0.0rc0.dist-info/RECORD
