Metadata-Version: 2.1
Name: langchain-extra
Version: 0.0.0rc0
Summary: Use langchain-extras
License: MIT
